crf_beam.cpython-39-x86_64-linux-gnu.so
crf_beam-0.1.9.dist-info/METADATA
crf_beam-0.1.9.dist-info/WHEEL
crf_beam-0.1.9.dist-info/top_level.txt
crf_beam-0.1.9.dist-info/RECORD
