Metadata-Version: 2.1
Name: crf-beam
Version: 0.1.9
Summary: crf beam search
Home-page: https://nanoporetech.com
Author: Oxford Nanoporetech Technologies, Ltd.
Author-email: support@nanoporetech.com
Requires-Dist: torch ==2.1.2
Requires-Dist: numpy <2
